cjdropshipping/__init__.py
cjdropshipping/cjdropshipping.py
cjdropshipping-0.0.1.dist-info/METADATA
cjdropshipping-0.0.1.dist-info/WHEEL
cjdropshipping-0.0.1.dist-info/top_level.txt
cjdropshipping-0.0.1.dist-info/RECORD
